{
  "slug": "passive-house-foundation-design",
  "title": "Passive House Foundation and Slab Edge Details",
  "metaDescription": "Insulated slabs, frost walls, and thermal break strategies for ground-contact assemblies.",
  "targetKeyword": "passive house foundation",
  "category": "Envelope",
  "wordCountTarget": 1500,
  "internalLinks": [
    "/passive-house/envelope"
  ],
  "affiliateCategories": [
    "insulation"
  ],
  "faqSchema": [],
  "outline": [
    "Slab insulation",
    "Edge details",
    "Basements",
    "PHI details"
  ]
}